{"ballot_style": "congress-district-5-lacroix", "contests": [{"ballot_selections": [{"is_placeholder_selection": false, "object_id": "barchi-hallaren-selection", "vote": "False"}, {"is_placeholder_selection": false, "object_id": "cramer-vuocolo-selection", "vote": "False"}, {"is_placeholder_selection": false, "object_id": "court-blumhardt-selection", "vote": "True"}, {"is_placeholder_selection": false, "object_id": "patterson-lariviere-selection", "vote": "False"}], "object_id": "president-vice-president-contest"}, {"ballot_selections": [{"is_placeholder_selection": false, "object_id": "harris-selection", "vote": "True"}, {"is_placeholder_selection": false, "object_id": "bargmann-selection", "vote": "False"}, {"is_placeholder_selection": false, "object_id": "steel-loy-selection", "vote": "False"}, {"is_placeholder_selection": false, "object_id": "williams-selection", "vote": "False"}, {"is_placeholder_selection": false, "object_id": "alpern-selection", "vote": "False"}, {"is_placeholder_selection": false, "object_id": "windbeck-selection", "vote": "False"}, {"is_placeholder_selection": false, "object_id": "alexander-selection", "vote": "False"}, {"is_placeholder_selection": false, "object_id": "lee-selection", "vote": "False"}, {"is_placeholder_selection": false, "object_id": "ash-selection", "vote": "False"}, {"is_placeholder_selection": false, "object_id": "kennedy-selection", "vote": "False"}, {"is_placeholder_selection": false, "object_id": "teller-selection", "vote": "False"}, {"is_placeholder_selection": false, "object_id": "ward-selection", "vote": "False"}, {"is_placeholder_selection": false, "object_id": "murphy-selection", "vote": "False"}, {"is_placeholder_selection": false, "object_id": "callanann-selection", "vote": "False"}, {"is_placeholder_selection": false, "object_id": "chandler-selection", "vote": "False"}, {"is_placeholder_selection": false, "object_id": "write-in-selection-governor", "vote": "False"}], "object_id": "ozark-governor"}, {"ballot_selections": [{"is_placeholder_selection": false, "object_id": "keller-selection", "vote": "False"}, {"is_placeholder_selection": false, "object_id": "rangel-selection", "vote": "True"}, {"is_placeholder_selection": false, "object_id": "witherspoon-smithson-selection", "vote": "False"}], "object_id": "congress-district-5-contest"}], "object_id": "ballot-e0cfa2b6-dd9a-11ea-9295-f45c89ba671b"}